myna/__init__.py
myna_python-0.1.0.dist-info/LICENSE
myna_python-0.1.0.dist-info/WHEEL
myna_python-0.1.0.dist-info/METADATA
myna_python-0.1.0.dist-info/RECORD
