Metadata-Version: 2.1
Name: myna-python
Version: 0.1.0
Summary: cli-tool/library for interacting with the 個人番号カード
License: Apache-2.0
Author: Yuichiro Smith
Author-email: contact@yu-smith.com
Requires-Python: >=3.6.2,<4.0
Classifier: License :: OSI Approved :: Apache Software License
Classifier: Programming Language :: Python :: 3
Classifier: Programming Language :: Python :: 3.7
Classifier: Programming Language :: Python :: 3.8
Classifier: Programming Language :: Python :: 3.9
Requires-Dist: cryptography (>=35.0.0,<36.0.0)
Requires-Dist: pyscard (>=2.0.2,<3.0.0)
Requires-Dist: typer (>=0.4.0,<0.5.0)
